pandas_polygon_api/__init__.py
pandas_polygon_api/mp_util.py
pandas_polygon_api/polygon_api.py
pandas_polygon_api-0.1.1.dist-info/LICENSE
pandas_polygon_api-0.1.1.dist-info/METADATA
pandas_polygon_api-0.1.1.dist-info/WHEEL
pandas_polygon_api-0.1.1.dist-info/top_level.txt
pandas_polygon_api-0.1.1.dist-info/RECORD
