Metadata-Version: 2.1
Name: pandas-polygon-api
Version: 0.1.1
Summary: Polygon end point accessed through pandas
Home-page: http://github.com/jamesyrose/pandas_polygon_api
Author: jamesyrose
Author-email: jyrose@vertet.io
License: MIT
Keywords: pandas,finance,numpy,analysis,algo trading,polygon
Platform: UNKNOWN
Requires-Dist: pandas
Requires-Dist: requests
